README.md
setup.cfg
setup.py
predickter/__init__.py
predickter/precrickter.py
predickter/precrickter_old.py
predickter.egg-info/PKG-INFO
predickter.egg-info/SOURCES.txt
predickter.egg-info/dependency_links.txt
predickter.egg-info/requires.txt
predickter.egg-info/top_level.txt