Metadata-Version: 1.1
Name: predickter
Version: 1.0.6
Summary: A library used for live cricket scores from cricbuzz
Home-page: https://github.com/dilipbobby/predickter
Author: dilipbobby
Author-email: dilipreddykiralam@gmail.com
License: MIT
Download-URL: https://github.com/dilipbobby/predickter/tarball/1.0.6
Keywords: cricket,cricbuzz,live cricket scores,live cricket
Platform: UNKNOWN
